data_collection/__init__.py
data_collection/__main__.py
data_collection/cli.py
data_collection/face_recognition/__init__.py
data_collection/face_recognition/api.py
data_collection/scripts/cull_unrecognized_faces.py
data_collection/scripts/download_youtube.py
data_collection/scripts/extract_faces.py
data_collection/scripts/extract_frames.py
data_collection-0.1.0.dist-info/entry_points.txt
data_collection-0.1.0.dist-info/WHEEL
data_collection-0.1.0.dist-info/METADATA
data_collection-0.1.0.dist-info/RECORD
