Metadata-Version: 2.1
Name: data-collection
Version: 0.1.0
Summary: Collection of scripts for compiling various forms of data for ML
License: MIT
Author: Andy Jackson
Author-email: amjack100@gmail.com
Requires-Python: >=3.8,<4.0
Classifier: License :: OSI Approved :: MIT License
Classifier: Programming Language :: Python :: 3
Classifier: Programming Language :: Python :: 3.8
Classifier: Programming Language :: Python :: 3.9
Requires-Dist: Pillow (>=8.1.2,<9.0.0)
Requires-Dist: dlib (>=19.21.1,<20.0.0)
Requires-Dist: face_recognition_models (>=0.3.0,<0.4.0)
Requires-Dist: fire (>=0.4.0,<0.5.0)
Requires-Dist: numpy (>=1.20.1,<2.0.0)
Requires-Dist: tqdm (>=4.59.0,<5.0.0)
